README.md
setup.py
common/__init__.py
common/customize_error.py
common/data_provider.py
common/html_reporter.py
common/my_logger.py
common/test_case_finder.py
common/test_decorator.py
common/test_filter.py
common/user_options.py
configs/__init__.py
configs/global_config.py
ktestpy.egg-info/PKG-INFO
ktestpy.egg-info/SOURCES.txt
ktestpy.egg-info/dependency_links.txt
ktestpy.egg-info/entry_points.txt
ktestpy.egg-info/not-zip-safe
ktestpy.egg-info/requires.txt
ktestpy.egg-info/top_level.txt
utilities/__init__.py
utilities/yaml_helper.py